gpx2exif/__init__.py
gpx2exif/common.py
gpx2exif/flickr_api_auth.py
gpx2exif/gpx2exif.py
gpx2exif/gpx2flickr.py
gpx2exif/main.py
gpx2exif-12.dist-info/LICENSE
gpx2exif-12.dist-info/METADATA
gpx2exif-12.dist-info/WHEEL
gpx2exif-12.dist-info/entry_points.txt
gpx2exif-12.dist-info/top_level.txt
gpx2exif-12.dist-info/RECORD
